<?xml version="1.0" encoding="utf-8"?>
<ClientInfos>
  <ClientInfo>
    <ClientID>D877CD07-F3A6-CBBC-D622-90000B1F2540</ClientID>
    <ActiveTime>05/24/2014 15:48:53</ActiveTime>
    <RefreshTime>05/24/2014 15:49:15</RefreshTime>
  </ClientInfo>
  <ClientInfo>
    <ClientID>8F7C5D10-9E5A-EFF8-16EB-19015510560E</ClientID>
    <ActiveTime>05/28/2014 09:20:21</ActiveTime>
    <RefreshTime>05/28/2014 09:20:30</RefreshTime>
  </ClientInfo>
  <ClientInfo>
    <ClientID>4ACF7ECA-6153-7DC4-06B1-C3E9FC63D527</ClientID>
    <ActiveTime>05/28/2014 09:21:05</ActiveTime>
    <RefreshTime>05/28/2014 09:21:12</RefreshTime>
  </ClientInfo>
</ClientInfos>